{"10":{"isoUnit":"DAY","mxUnit":"Days","sapDisplayUnit":"D"},"%":{"isoUnit":"P1","mxUnit":"%","sapDisplayUnit":"%"},"%O":{"isoUnit":"","mxUnit":"%0","sapDisplayUnit":"%O"},"2M":{"isoUnit":"2M","mxUnit":"cm/s","sapDisplayUnit":"CMS"},"2X":{"isoUnit":"2","mxUnit":"m/min","sapDisplayUnit":"000"},"4G":{"isoUnit":"4G","mxUnit":"µl","sapDisplayUnit":"µL"},"4O":{"isoUnit":"4O","mxUnit":"µF","sapDisplayUnit":"µF"},"4T":{"isoUnit":"4T","mxUnit":"pF","sapDisplayUnit":"PF"},"A87":{"isoUnit":"A87","mxUnit":"GOhm","sapDisplayUnit":"GOH"},"A93":{"isoUnit":"A93","mxUnit":"g/m3","sapDisplayUnit":"GM3"},"ACR":{"isoUnit":"","mxUnit":"Acre","sapDisplayUnit":"ACR"},"B34":{"isoUnit":"B34","mxUnit":"kg/dm3","sapDisplayUnit":"KD3"},"B45":{"isoUnit":"B45","mxUnit":"kmol","sapDisplayUnit":"KML"},"B47":{"isoUnit":"B47","mxUnit":"ND","sapDisplayUnit":"NI"},"B73":{"isoUnit":"B73","mxUnit":"MN","sapDisplayUnit":"MN"},"B75":{"isoUnit":"B75","mxUnit":"MOhm","sapDisplayUnit":"MGO"},"B78":{"isoUnit":"B78","mxUnit":"MV","sapDisplayUnit":"MHV"},"B84":{"isoUnit":"B84","mxUnit":"µA","sapDisplayUnit":"µA"},"BAG":{"isoUnit":"BG","mxUnit":"Bag","sapDisplayUnit":"BAG"},"BOT":{"isoUnit":"BO","mxUnit":"Bottle","sapDisplayUnit":"BT"},"C10":{"isoUnit":"C10","mxUnit":"mF","sapDisplayUnit":"RF"},"C36":{"isoUnit":"C36","mxUnit":"Mo/m3","sapDisplayUnit":"M/M"},"C38":{"isoUnit":"C38","mxUnit":"Mol/Liter","sapDisplayUnit":"M/L"},"C39":{"isoUnit":"C39","mxUnit":"nA","sapDisplayUnit":"NA"},"C3S":{"isoUnit":"2J","mxUnit":"cm3/s","sapDisplayUnit":"C3S"},"C41":{"isoUnit":"C41","mxUnit":"nF","sapDisplayUnit":"R-U"},"C56":{"isoUnit":"C56","mxUnit":"N/mm2","sapDisplayUnit":"NMM"},"CCM":{"isoUnit":"CMQ","mxUnit":"cm3","sapDisplayUnit":"CCM"},"CDM":{"isoUnit":"DMQ","mxUnit":"Cubicdec.","sapDisplayUnit":"CD3"},"CM":{"isoUnit":"CMT","mxUnit":"cm","sapDisplayUnit":"CM"},"CM2":{"isoUnit":"CMK","mxUnit":"cm2","sapDisplayUnit":"CM2"},"CS":{"isoUnit":"CS","mxUnit":"Case","sapDisplayUnit":"CV"},"CTL":{"isoUnit":"","mxUnit":"Centiliter","sapDisplayUnit":"CL"},"D10":{"isoUnit":"D10","mxUnit":"Siemens/m","sapDisplayUnit":"S/M"},"D41":{"isoUnit":"D41","mxUnit":"t/m3","sapDisplayUnit":"TOM"},"D46":{"isoUnit":"D46","mxUnit":"VA","sapDisplayUnit":"VAM"},"DEG":{"isoUnit":"DD","mxUnit":"Degree","sapDisplayUnit":"DEG"},"DM":{"isoUnit":"DMT","mxUnit":"dm","sapDisplayUnit":"DM"},"DR":{"isoUnit":"DR","mxUnit":"Drum","sapDisplayUnit":"DR"},"DZ":{"isoUnit":"DZN","mxUnit":"Dozen","sapDisplayUnit":"DZ"},"EA":{"isoUnit":"EA","mxUnit":"each","sapDisplayUnit":"EA"},"EE":{"isoUnit":"","mxUnit":"Enzy.Units","sapDisplayUnit":"EU"},"EML":{"isoUnit":"","mxUnit":"Enzyme/ml","sapDisplayUnit":"EML"},"FT":{"isoUnit":"","mxUnit":"Foot","sapDisplayUnit":"FT"},"FT2":{"isoUnit":"","mxUnit":"Squareft","sapDisplayUnit":"FT2"},"FT3":{"isoUnit":"","mxUnit":"Cubicft","sapDisplayUnit":"FT3"},"G":{"isoUnit":"GRM","mxUnit":"g","sapDisplayUnit":"G"},"G/L":{"isoUnit":"","mxUnit":"gai/liter","sapDisplayUnit":"G/L"},"GAU":{"isoUnit":"","mxUnit":"GramGold","sapDisplayUnit":"GAU"},"GJ":{"isoUnit":"","mxUnit":"Gigajoule","sapDisplayUnit":"GJ"},"GLI":{"isoUnit":"GL","mxUnit":"g/l","sapDisplayUnit":"GLI"},"GLL":{"isoUnit":"","mxUnit":"USgallon","sapDisplayUnit":"GAL"},"GLM":{"isoUnit":"","mxUnit":"Gal/Mi(US)","sapDisplayUnit":"GPM"},"GM":{"isoUnit":"","mxUnit":"g/mol","sapDisplayUnit":"GM"},"GM2":{"isoUnit":"","mxUnit":"g/m2","sapDisplayUnit":"GM2"},"GPH":{"isoUnit":"","mxUnit":"Gal/hrUS","sapDisplayUnit":"GPH"},"GQ":{"isoUnit":"GQ","mxUnit":"µg/m3","sapDisplayUnit":"µGQ"},"GRO":{"isoUnit":"GRO","mxUnit":"Gross","sapDisplayUnit":"GRO"},"GW":{"isoUnit":"","mxUnit":"gact.ing.","sapDisplayUnit":"GAI"},"H":{"isoUnit":"","mxUnit":"Hour","sapDisplayUnit":"H"},"HAR":{"isoUnit":"","mxUnit":"Hectare","sapDisplayUnit":"HA"},"HL":{"isoUnit":"HLT","mxUnit":"hl","sapDisplayUnit":"HL"},"IN":{"isoUnit":"INH","mxUnit":"Inches","sapDisplayUnit":"\""},"IN2":{"isoUnit":"","mxUnit":"Inch2","sapDisplayUnit":"\"2"},"IN3":{"isoUnit":"","mxUnit":"Cubicinch","sapDisplayUnit":"\"3"},"JHR":{"isoUnit":"ANN","mxUnit":"Year","sapDisplayUnit":"YR"},"JKG":{"isoUnit":"","mxUnit":"J/kg","sapDisplayUnit":"JKG"},"JKK":{"isoUnit":"B11","mxUnit":"J/(kg*K)","sapDisplayUnit":"JKK"},"JMO":{"isoUnit":"","mxUnit":"J/mol","sapDisplayUnit":"JMO"},"KAN":{"isoUnit":"CA","mxUnit":"Canister","sapDisplayUnit":"CAN"},"KAR":{"isoUnit":"CT","mxUnit":"Carton","sapDisplayUnit":"CAR"},"KG":{"isoUnit":"KGM","mxUnit":"kg","sapDisplayUnit":"KG"},"KGM":{"isoUnit":"","mxUnit":"kg/mol","sapDisplayUnit":"KGM"},"KGS":{"isoUnit":"KGS","mxUnit":"kg/s","sapDisplayUnit":"KGS"},"KGV":{"isoUnit":"KMQ","mxUnit":"kg/m3","sapDisplayUnit":"KGV"},"KGW":{"isoUnit":"","mxUnit":"kgac.ing.","sapDisplayUnit":"KAI"},"KI":{"isoUnit":"B","mxUnit":"Crate","sapDisplayUnit":"CRT"},"KJK":{"isoUnit":"","mxUnit":"KJ/kg","sapDisplayUnit":"KJK"},"KJM":{"isoUnit":"","mxUnit":"KJ/mol","sapDisplayUnit":"KJM"},"KM":{"isoUnit":"KMT","mxUnit":"km","sapDisplayUnit":"KM"},"KM2":{"isoUnit":"","mxUnit":"km2","sapDisplayUnit":"KM2"},"KMH":{"isoUnit":"KMH","mxUnit":"km/h","sapDisplayUnit":"KMH"},"KMN":{"isoUnit":"","mxUnit":"K/min","sapDisplayUnit":"KMN"},"KMS":{"isoUnit":"","mxUnit":"K/s","sapDisplayUnit":"KMS"},"KPA":{"isoUnit":"KPA","mxUnit":"kPa","sapDisplayUnit":"KPA"},"KT":{"isoUnit":"","mxUnit":"kt","sapDisplayUnit":"KT"},"KVA":{"isoUnit":"KVA","mxUnit":"kVA","sapDisplayUnit":"KVA"},"KWK":{"isoUnit":"","mxUnit":"kai/kg","sapDisplayUnit":"KIK"},"L":{"isoUnit":"LTR","mxUnit":"l","sapDisplayUnit":"L"},"L2":{"isoUnit":"L2","mxUnit":"l/min","sapDisplayUnit":"LMI"},"LB":{"isoUnit":"","mxUnit":"Pound","sapDisplayUnit":"LB"},"LE":{"isoUnit":"C62","mxUnit":"AU","sapDisplayUnit":"AU"},"LHK":{"isoUnit":"","mxUnit":"l/100km","sapDisplayUnit":"LHK"},"LMS":{"isoUnit":"","mxUnit":"l/mol.s","sapDisplayUnit":"LMS"},"LPH":{"isoUnit":"","mxUnit":"Liter/hr","sapDisplayUnit":"LPH"},"M":{"isoUnit":"MTR","mxUnit":"m","sapDisplayUnit":"M"},"M/S":{"isoUnit":"MTS","mxUnit":"m/s","sapDisplayUnit":"M/S"},"M2":{"isoUnit":"MTK","mxUnit":"m2","sapDisplayUnit":"M2"},"M2I":{"isoUnit":"","mxUnit":"1/M2","sapDisplayUnit":"M-2"},"M2S":{"isoUnit":"S4","mxUnit":"m2/s","sapDisplayUnit":"M2S"},"M3":{"isoUnit":"MTQ","mxUnit":"m3","sapDisplayUnit":"M3"},"M3D":{"isoUnit":"","mxUnit":"m3/day","sapDisplayUnit":"M3D"},"M3S":{"isoUnit":"MQS","mxUnit":"m3/s","sapDisplayUnit":"M3S"},"MEJ":{"isoUnit":"","mxUnit":"MJ","sapDisplayUnit":"MEJ"},"MG":{"isoUnit":"MGM","mxUnit":"mg","sapDisplayUnit":"MG"},"MGL":{"isoUnit":"M1","mxUnit":"mg/l","sapDisplayUnit":"MGL"},"MGQ":{"isoUnit":"GP","mxUnit":"mg/m3","sapDisplayUnit":"MGQ"},"MI":{"isoUnit":"SMI","mxUnit":"Mile","sapDisplayUnit":"MI"},"MI2":{"isoUnit":"","mxUnit":"Mile2","sapDisplayUnit":"MI2"},"MIM":{"isoUnit":"4H","mxUnit":"µm","sapDisplayUnit":"µM"},"MIN":{"isoUnit":"MIN","mxUnit":"min.","sapDisplayUnit":"MIN"},"MIS":{"isoUnit":"B98","mxUnit":"µs","sapDisplayUnit":"MIS"},"ML":{"isoUnit":"MLT","mxUnit":"ml","sapDisplayUnit":"ML"},"MLW":{"isoUnit":"","mxUnit":"mlact.in.","sapDisplayUnit":"MLI"},"MM":{"isoUnit":"MMT","mxUnit":"mm","sapDisplayUnit":"MM"},"MM2":{"isoUnit":"MMK","mxUnit":"mm2","sapDisplayUnit":"MM2"},"MMQ":{"isoUnit":"MMQ","mxUnit":"mm3","sapDisplayUnit":"MM3"},"MNM":{"isoUnit":"","mxUnit":"mN/m","sapDisplayUnit":"MNM"},"MON":{"isoUnit":"MON","mxUnit":"Months","sapDisplayUnit":"MON"},"MPG":{"isoUnit":"","mxUnit":"Mi/Gal(US)","sapDisplayUnit":"MPG"},"MPS":{"isoUnit":"C24","mxUnit":"mPa.s","sapDisplayUnit":"MPS"},"MQH":{"isoUnit":"MQH","mxUnit":"m3/h","sapDisplayUnit":"M3H"},"MS":{"isoUnit":"C26","mxUnit":"ms","sapDisplayUnit":"MSE"},"MS2":{"isoUnit":"MSK","mxUnit":"m/s2","sapDisplayUnit":"MS2"},"MTS":{"isoUnit":"MTS","mxUnit":"m/h","sapDisplayUnit":"M/H"},"MVA":{"isoUnit":"MVA","mxUnit":"MVA","sapDisplayUnit":"MVA"},"MWH":{"isoUnit":"","mxUnit":"MWh","sapDisplayUnit":"MWH"},"NAM":{"isoUnit":"C45","mxUnit":"nm","sapDisplayUnit":"NAM"},"NM":{"isoUnit":"","mxUnit":"N/m","sapDisplayUnit":"NM"},"NS":{"isoUnit":"C47","mxUnit":"ns","sapDisplayUnit":"NS"},"OCM":{"isoUnit":"C60","mxUnit":"Ohm*cm","sapDisplayUnit":"OCM"},"OM":{"isoUnit":"C61","mxUnit":"Ohm*m","sapDisplayUnit":"OM"},"OZ":{"isoUnit":"ONZ","mxUnit":"Ounce","sapDisplayUnit":"OZ"},"OZA":{"isoUnit":"","mxUnit":"Fld.ozUS","sapDisplayUnit":"FOZ"},"P":{"isoUnit":"","mxUnit":"Points","sapDisplayUnit":"P"},"PAA":{"isoUnit":"PR","mxUnit":"Pair","sapDisplayUnit":"PAA"},"PAK":{"isoUnit":"PK","mxUnit":"Pack","sapDisplayUnit":"PAC"},"PAL":{"isoUnit":"PF","mxUnit":"Pallet","sapDisplayUnit":"PAL"},"PAS":{"isoUnit":"C65","mxUnit":"Pascalsec","sapDisplayUnit":"PAS"},"PCT":{"isoUnit":"","mxUnit":"Groupprop","sapDisplayUnit":"PRC"},"PMI":{"isoUnit":"","mxUnit":"1/min","sapDisplayUnit":"PMI"},"PMR":{"isoUnit":"","mxUnit":"kg/m2*s","sapDisplayUnit":"PMR"},"PPB":{"isoUnit":"","mxUnit":"ppb","sapDisplayUnit":"PPB"},"PPM":{"isoUnit":"59","mxUnit":"ppm","sapDisplayUnit":"PPM"},"PPT":{"isoUnit":"","mxUnit":"ppt","sapDisplayUnit":"PPT"},"PRM":{"isoUnit":"","mxUnit":"ug/cm2*min","sapDisplayUnit":"PRM"},"PRS":{"isoUnit":"IE","mxUnit":"Persons","sapDisplayUnit":"PRS"},"PS":{"isoUnit":"","mxUnit":"ps","sapDisplayUnit":"PS"},"PT":{"isoUnit":"","mxUnit":"PintUSl","sapDisplayUnit":"PT"},"QT":{"isoUnit":"","mxUnit":"QuartUSl","sapDisplayUnit":"QT"},"RHO":{"isoUnit":"23","mxUnit":"g/cm3","sapDisplayUnit":"RHO"},"ROL":{"isoUnit":"RO","mxUnit":"Role","sapDisplayUnit":"ROL"},"ST":{"isoUnit":"PCE","mxUnit":"Piece","sapDisplayUnit":"PC"},"STD":{"isoUnit":"HUR","mxUnit":"Hours","sapDisplayUnit":"HR"},"TAG":{"isoUnit":"DAY","mxUnit":"Days","sapDisplayUnit":"DAY"},"TH":{"isoUnit":"MIL","mxUnit":"Thousands","sapDisplayUnit":"TS"},"TO":{"isoUnit":"TNE","mxUnit":"t","sapDisplayUnit":"TO"},"TON":{"isoUnit":"STN","mxUnit":"USTon","sapDisplayUnit":"TON"},"TST":{"isoUnit":"","mxUnit":"","sapDisplayUnit":"001"},"UGL":{"isoUnit":"","mxUnit":"µg/l","sapDisplayUnit":"µGL"},"V01":{"isoUnit":"","mxUnit":"µS/cm","sapDisplayUnit":"MSC"},"V02":{"isoUnit":"C36","mxUnit":"Millimol/l","sapDisplayUnit":"MPL"},"VAL":{"isoUnit":"","mxUnit":"Value","sapDisplayUnit":"VAL"},"WCH":{"isoUnit":"WEE","mxUnit":"Weeks","sapDisplayUnit":"WK"},"WMK":{"isoUnit":"D53","mxUnit":"W/(m*K)","sapDisplayUnit":"WMK"},"WTL":{"isoUnit":"","mxUnit":"kg/s*m2","sapDisplayUnit":"WKY"},"YD":{"isoUnit":"","mxUnit":"Yards","sapDisplayUnit":"YD"},"YD2":{"isoUnit":"","mxUnit":"Yard2","sapDisplayUnit":"YD2"},"YD3":{"isoUnit":"","mxUnit":"Cubicyard","sapDisplayUnit":"YD3"},"kgb":{"isoUnit":"","mxUnit":"kg/bbl","sapDisplayUnit":"kgb"}}